basic_math_calculator/__init__.py
basic_math_calculator/calculator.py
basic_math_calculator-0.1.0.dist-info/LICENSE
basic_math_calculator-0.1.0.dist-info/WHEEL
basic_math_calculator-0.1.0.dist-info/METADATA
basic_math_calculator-0.1.0.dist-info/RECORD
