Metadata-Version: 2.1
Name: basic_math_calculator
Version: 0.1.0
Summary: Very simple calculator 
Author: SigisM
Classifier: License :: OSI Approved :: MIT License
Project-URL: Home, https://github.com/SigisM/Calculator
